NasrPy/__init__.py
DevilPy-0.7.dist-info/METADATA
DevilPy-0.7.dist-info/WHEEL
DevilPy-0.7.dist-info/top_level.txt
DevilPy-0.7.dist-info/RECORD
