Metadata-Version: 2.1
Name: DevilPy
Version: 0.7
Summary: A powerful encryption libraries in Python created by the NasrPy
Author: DevilPy
Classifier: Programming Language :: Python :: 3
